README.md
setup.py
Django_Smile_Serializer.egg-info/PKG-INFO
Django_Smile_Serializer.egg-info/SOURCES.txt
Django_Smile_Serializer.egg-info/dependency_links.txt
Django_Smile_Serializer.egg-info/requires.txt
Django_Smile_Serializer.egg-info/top_level.txt
SmileSerializer/TimeFactory.py
SmileSerializer/__init__.py
SmileSerializer/serializer.py