Metadata-Version: 1.2
Name: Django-Smile-Serializer
Version: 1.0.5
Summary: Django-Smile-Serializer
Home-page: https://github.com/lpig/Django-Smile-Serializer
Maintainer: l-pig
Maintainer-email: o55662000@yeah.net
License: UNKNOWN
Platform: UNKNOWN
